sqlite_migration_manager/__init__.py
sqlite_migration_manager/manager.py
sqlite_migration_manager-1.0.0.dist-info/METADATA
sqlite_migration_manager-1.0.0.dist-info/WHEEL
sqlite_migration_manager-1.0.0.dist-info/licenses/LICENSE
sqlite_migration_manager-1.0.0.dist-info/RECORD
