Metadata-Version: 2.3
Name: sqlite-migration-manager
Version: 1.0.0
Summary: A SQLite database migration management library
Project-URL: Homepage, https://github.com/nbr23/sqlite-migration-manager
Project-URL: Bug Tracker, https://github.com/nbr23/sqlite-migration-manager/issues
Author-email: nbr23 <max@23.tf>
License-File: LICENSE
Requires-Python: >=3.7
Provides-Extra: dev
Requires-Dist: pytest; extra == 'dev'
